pathschema/__init__.py
pathschema/__main__.py
pathschema/exceptions.py
pathschema/models.py
pathschema/parser.py
pathschema/utils.py
pathschema/validator.py
pathschema-0.2.1.dist-info/METADATA
pathschema-0.2.1.dist-info/WHEEL
pathschema-0.2.1.dist-info/licenses/LICENSE
pathschema-0.2.1.dist-info/RECORD
