Metadata-Version: 2.1
Name: pathschema
Version: 0.2.1
Summary: Standardize and plan out a file structure!
Project-URL: Source, https://github.com/Apollo-Roboto/python-pathschema
Author-email: Apollo-Roboto <Apollo_Roboto@outlook.com>
License-Expression: MIT
License-File: LICENSE
Keywords: Directory,File,File System,Folder,Schema,Validation
Classifier: License :: OSI Approved :: MIT License
Classifier: Natural Language :: English
Classifier: Operating System :: OS Independent
Classifier: Programming Language :: Python :: 3
Classifier: Programming Language :: Python :: 3.9
Classifier: Programming Language :: Python :: 3.10
Classifier: Programming Language :: Python :: 3.11
Classifier: Topic :: Software Development :: Libraries
Classifier: Topic :: Software Development :: Libraries :: Python Modules
Classifier: Topic :: System :: Filesystems
Classifier: Topic :: Utilities
Classifier: Typing :: Typed
Requires-Python: >=3.9
Requires-Dist: colorama==0.4.6
